{
  "clients": [
    {
      "name": "David",
      "business": "NOW",
      "email": "david@now.tienda",
      "phone": "693333353",
      "notes": "Soy el king",
      "id": 1
    },
    {
      "name": "Ali",
      "business": "Pelotuda",
      "email": "ali@pelotuda.com",
      "phone": "666666666",
      "notes": "Ali es una pelotuda",
      "id": 2
    },
    {
      "name": "Papa",
      "business": "Drones Andaluces",
      "email": "papa@papa.com",
      "phone": "687580605",
      "notes": "Drones",
      "id": 3
    },
    {
      "name": "Pikachu",
      "business": "Pokemon",
      "email": "pikachu@pokemon.com",
      "phone": "666777888",
      "notes": "Pika Pika",
      "id": 4
    },
    {
      "name": "fgdfg",
      "business": "dfgdfg",
      "email": "dfgdf@gmail.com",
      "phone": "45345",
      "notes": "345dfsg",
      "id": 5
    },
    {
      "name": "efgdfg",
      "business": "dfgdfg@gmail.com",
      "email": "sdfsdf@gmail.com",
      "phone": "345345",
      "notes": "dfgdf",
      "id": 6
    }
  ]
}